auger_oca/OCA.dat
auger_oca/__init__.py
auger_oca/auger_driver.py
auger_oca/basis_id.py
auger_oca/initi.py
auger_oca/input_parse.py
auger_oca/mbs.py
auger_oca/my_variables.py
auger_oca/oca_integrals.py
auger_oca/orbtransf_sz.py
auger_oca/rt2mzz.py
auger_oca/symm.py
auger_oca-2.0.0.dist-info/METADATA
auger_oca-2.0.0.dist-info/WHEEL
auger_oca-2.0.0.dist-info/licenses/LICENSE
auger_oca-2.0.0.dist-info/RECORD
