Metadata-Version: 2.1
Name: auger_oca
Version: 2.0.0
Summary: An Auger tool based on the one-center approximatio to be used with OpenMolcas
Project-URL: Homepage, https://gitlab.com/Molcas/OpenMolcas.git
Author-email: Bruno Tenorio <b.nunes.bruno@gmail.com>
License-File: LICENSE
Classifier: License :: OSI Approved :: MIT License
Classifier: Operating System :: OS Independent
Classifier: Programming Language :: Python :: 3
Requires-Python: >=3.7
